odoo8_addon_l10n_ch_credit_control_payment_slip_report-8.0.1.3.0.99.dev19-py2.7-nspkg.pth
odoo8_addon_l10n_ch_credit_control_payment_slip_report-8.0.1.3.0.99.dev19.dist-info/METADATA
odoo8_addon_l10n_ch_credit_control_payment_slip_report-8.0.1.3.0.99.dev19.dist-info/RECORD
odoo8_addon_l10n_ch_credit_control_payment_slip_report-8.0.1.3.0.99.dev19.dist-info/WHEEL
odoo8_addon_l10n_ch_credit_control_payment_slip_report-8.0.1.3.0.99.dev19.dist-info/namespace_packages.txt
odoo8_addon_l10n_ch_credit_control_payment_slip_report-8.0.1.3.0.99.dev19.dist-info/top_level.txt
odoo_addons/l10n_ch_credit_control_payment_slip_report/__init__.py
odoo_addons/l10n_ch_credit_control_payment_slip_report/__openerp__.py
odoo_addons/l10n_ch_credit_control_payment_slip_report/account_move_line.py
odoo_addons/l10n_ch_credit_control_payment_slip_report/credit_control_communication_report.py
odoo_addons/l10n_ch_credit_control_payment_slip_report/credit_control_printer.py
odoo_addons/l10n_ch_credit_control_payment_slip_report/credit_control_printer_view.xml
odoo_addons/l10n_ch_credit_control_payment_slip_report/payment_slip.py
odoo_addons/l10n_ch_credit_control_payment_slip_report/report.xml
odoo_addons/l10n_ch_credit_control_payment_slip_report/i18n/am.po
odoo_addons/l10n_ch_credit_control_payment_slip_report/i18n/ar.po
odoo_addons/l10n_ch_credit_control_payment_slip_report/i18n/bg.po
odoo_addons/l10n_ch_credit_control_payment_slip_report/i18n/bs.po
odoo_addons/l10n_ch_credit_control_payment_slip_report/i18n/ca.po
odoo_addons/l10n_ch_credit_control_payment_slip_report/i18n/cs.po
odoo_addons/l10n_ch_credit_control_payment_slip_report/i18n/da.po
odoo_addons/l10n_ch_credit_control_payment_slip_report/i18n/de.po
odoo_addons/l10n_ch_credit_control_payment_slip_report/i18n/el_GR.po
odoo_addons/l10n_ch_credit_control_payment_slip_report/i18n/en_GB.po
odoo_addons/l10n_ch_credit_control_payment_slip_report/i18n/es.po
odoo_addons/l10n_ch_credit_control_payment_slip_report/i18n/es_AR.po
odoo_addons/l10n_ch_credit_control_payment_slip_report/i18n/es_CO.po
odoo_addons/l10n_ch_credit_control_payment_slip_report/i18n/es_CR.po
odoo_addons/l10n_ch_credit_control_payment_slip_report/i18n/es_EC.po
odoo_addons/l10n_ch_credit_control_payment_slip_report/i18n/es_MX.po
odoo_addons/l10n_ch_credit_control_payment_slip_report/i18n/es_PE.po
odoo_addons/l10n_ch_credit_control_payment_slip_report/i18n/es_VE.po
