Metadata-Version: 2.1
Name: odoo8-addon-l10n-ch-credit-control-payment-slip-report
Version: 8.0.1.3.0.99.dev19
Summary: Print BVR/ESR slip related to credit control
Home-page: http://www.camptocamp.com
Author: Camptocamp,Odoo Community Association (OCA)
Author-email: support@odoo-community.org
License: AGPL-3
Platform: UNKNOWN
Classifier: Programming Language :: Python
Classifier: Framework :: Odoo
Classifier: License :: OSI Approved :: GNU Affero General Public License v3
Requires-Python: ~=2.7
Requires-Dist: odoo8-addon-account-credit-control
Requires-Dist: odoo8-addon-account-credit-control-dunning-fees
Requires-Dist: odoo8-addon-l10n-ch-payment-slip
Requires-Dist: odoo (<9.0a,>=8.0a)
